zyra/README.md
zyra/__init__.py
zyra/api/README.md
zyra/api/__init__.py
zyra/api/mcp_tools/README.md
zyra/api/mcp_tools/audio.py
zyra/api/mcp_tools/generic.py
zyra/api/models/cli_request.py
zyra/api/models/domain_api.py
zyra/api/models/types.py
zyra/api/routers/api_generic.py
zyra/api/routers/cli.py
zyra/api/routers/domain_acquire.py
zyra/api/routers/domain_assets.py
zyra/api/routers/domain_decide.py
zyra/api/routers/domain_disseminate.py
zyra/api/routers/domain_narrate.py
zyra/api/routers/domain_process.py
zyra/api/routers/domain_simulate.py
zyra/api/routers/domain_transform.py
zyra/api/routers/domain_verify.py
zyra/api/routers/domain_visualize.py
zyra/api/routers/files.py
zyra/api/routers/jobs.py
zyra/api/routers/manifest.py
zyra/api/routers/mcp.py
zyra/api/routers/search.py
zyra/api/routers/ws.py
zyra/api/schemas/domain_args.py
zyra/api/security.py
zyra/api/server.py
zyra/api/services/manifest.py
zyra/api/utils/assets.py
zyra/api/utils/errors.py
zyra/api/utils/obs.py
zyra/api/workers/executor.py
zyra/api/workers/jobs.py
zyra/api_cli.py
zyra/assets/__init__.py
zyra/assets/ascii/logo_ascii_tree_tiny.txt
zyra/assets/images/__init__.py
zyra/assets/images/dark-gray.jpg
zyra/assets/images/earth_vegetation.jpg
zyra/assets/images/eic-smoke-basemap.jpg
zyra/assets/images/eic-smoke-overlay.png
zyra/assets/images/fv3-chem-basemap.jpg
zyra/assets/images/imagery.jpg
zyra/assets/llm/README.md
zyra/assets/llm/actions/.gitkeep
zyra/assets/llm/presets/narrate/accessibility_default.yaml
zyra/assets/llm/presets/narrate/kids_policy_basic.yaml
zyra/assets/llm/presets/narrate/kids_policy_dual.yaml
zyra/assets/llm/presets/narrate/kids_story.yaml
zyra/assets/llm/presets/narrate/multi_audience_report.yaml
zyra/assets/llm/presets/narrate/policy_brief.yaml
zyra/assets/llm/presets/narrate/scientific_lite.yaml
zyra/assets/llm/presets/narrate/scientific_rigorous.yaml
zyra/assets/llm/presets/narrate/stress_benchmark.yaml
zyra/assets/llm/prompts/.gitkeep
zyra-0.1.43.dist-info/METADATA
zyra-0.1.43.dist-info/WHEEL
zyra-0.1.43.dist-info/entry_points.txt
zyra-0.1.43.dist-info/licenses/LICENSE
zyra-0.1.43.dist-info/licenses/NOTICE
zyra-0.1.43.dist-info/RECORD
