Metadata-Version: 2.4
Name: zyra
Version: 0.1.43
Summary: A tool to ingest data from various sources and formats, create imagery or video based on that data, and send the results to various locations for dissemination.
License: Apache-2.0
License-File: LICENSE
License-File: NOTICE
Author: Eric Hackathorn
Author-email: eric.j.hackathorn@noaa.gov
Requires-Python: >=3.10,<4.0
Classifier: License :: OSI Approved :: Apache Software License
Classifier: Programming Language :: Python :: 3
Classifier: Programming Language :: Python :: 3.10
Classifier: Programming Language :: Python :: 3.11
Classifier: Programming Language :: Python :: 3.12
Classifier: Programming Language :: Python :: 3.13
Classifier: Programming Language :: Python :: 3.14
Provides-Extra: all
Provides-Extra: api
Provides-Extra: connectors
Provides-Extra: datatransfer
Provides-Extra: geotiff
Provides-Extra: grib2
Provides-Extra: guardrails
Provides-Extra: interactive
Provides-Extra: llm
Provides-Extra: mime
Provides-Extra: netcdf
Provides-Extra: processing
Provides-Extra: visualization
Provides-Extra: wizard
Provides-Extra: ws
Requires-Dist: PyVimeo (>=1.0,<2.0) ; extra == "datatransfer" or extra == "connectors" or extra == "all"
Requires-Dist: boto3 (>=1.17,<2.0) ; extra == "datatransfer" or extra == "connectors" or extra == "all"
Requires-Dist: cartopy (>=0.22.0,<0.23.0) ; extra == "visualization" or extra == "all"
Requires-Dist: cfgrib (>=0.9.12.0,<0.10.0.0) ; extra == "processing" or extra == "grib2" or extra == "all"
Requires-Dist: fastapi (>=0.120.2,<0.122.0) ; extra == "all" or extra == "api"
Requires-Dist: ffmpeg-python (>=0.2.0,<0.3.0) ; extra == "processing" or extra == "all"
Requires-Dist: google-auth (>=2.29.0,<3.0.0) ; extra == "llm" or extra == "all"
Requires-Dist: guardrails-ai (>=0.5.0,<0.6.0) ; extra == "guardrails"
Requires-Dist: matplotlib (>=3.8.3,<4.0.0) ; extra == "visualization" or extra == "all"
Requires-Dist: netcdf4 (>=1.6.5,<2.0.0) ; extra == "processing" or extra == "netcdf" or extra == "all"
Requires-Dist: numpy (>=1.26,<2.0)
Requires-Dist: prompt_toolkit (>=3.0.50,<4.0.0) ; extra == "wizard" or extra == "all"
Requires-Dist: pygrib (>=2.1.5,<3.0.0) ; extra == "processing" or extra == "grib2" or extra == "all"
Requires-Dist: python-dotenv (>=1.0.0,<2.0.0)
Requires-Dist: python-magic (>=0.4.27,<0.5.0) ; extra == "all" or extra == "mime"
Requires-Dist: python-multipart (>=0.0.18) ; extra == "all" or extra == "api"
Requires-Dist: pyyaml (>=6.0.2,<7.0.0)
Requires-Dist: rasterio (>=1.3.9,<2.0.0) ; extra == "processing" or extra == "geotiff" or extra == "all"
Requires-Dist: redis (>=5.0.0,<6.0.0) ; extra == "all" or extra == "api"
Requires-Dist: requests (>=2.25,<3.0) ; extra == "datatransfer" or extra == "connectors" or extra == "llm" or extra == "all"
Requires-Dist: reverse-geocoder (>=1.5.1,<2.0.0)
Requires-Dist: rioxarray (>=0.15.5,<0.16.0) ; extra == "processing" or extra == "geotiff" or extra == "all"
Requires-Dist: rq (>=1.15.1,<2.0.0) ; extra == "all" or extra == "api"
Requires-Dist: scipy (>=1.12.0,<2.0.0) ; extra == "processing" or extra == "visualization" or extra == "all"
Requires-Dist: siphon (>=0.9,<0.10) ; extra == "processing" or extra == "all"
Requires-Dist: uvicorn (>=0.30.0,<0.31.0) ; extra == "all" or extra == "api"
Requires-Dist: websockets (>=11.0.3,<12.0.0) ; extra == "ws"
Requires-Dist: xarray (>=2024.3.0,<2025.0.0) ; extra == "processing" or extra == "visualization" or extra == "netcdf" or extra == "all"
Project-URL: Documentation, https://github.com/NOAA-GSL/zyra/blob/main/README.md
Project-URL: Homepage, https://github.com/NOAA-GSL/zyra
Project-URL: Source, https://github.com/NOAA-GSL/zyra
Project-URL: Tracker, https://github.com/NOAA-GSL/zyra/issues
